README.rst
setup.cfg
setup.py
gp/__init__.py
gp.recipe.phantomjs.egg-info/PKG-INFO
gp.recipe.phantomjs.egg-info/SOURCES.txt
gp.recipe.phantomjs.egg-info/dependency_links.txt
gp.recipe.phantomjs.egg-info/entry_points.txt
gp.recipe.phantomjs.egg-info/namespace_packages.txt
gp.recipe.phantomjs.egg-info/not-zip-safe
gp.recipe.phantomjs.egg-info/requires.txt
gp.recipe.phantomjs.egg-info/top_level.txt
gp/recipe/__init__.py
gp/recipe/phantomjs/__init__.py
gp/recipe/phantomjs/script.py
gp/recipe/phantomjs/tests/__init__.py
gp/recipe/phantomjs/tests/test_init.py