Metadata-Version: 1.1
Name: gp.recipe.phantomjs
Version: 1.9.7.0
Summary: buildout recipe to install phantomjs/casperjs
Home-page: http://github.com/gawel/gp.recipe.phantomjs
Author: Gael Pasgrimaud
Author-email: gael@gawel.org
License: gpl
Keywords: buildout phantomjs casperjs
Platform: UNKNOWN
Classifier: Framework :: Buildout
Classifier: Intended Audience :: Developers
Classifier: Topic :: Software Development :: Build Tools
